{"openapi":"3.1.0","info":{"title":"OpenAPI definition","version":"v0"},"servers":[{"url":"http://localhost:8080","description":"Generated server url"}],"tags":[{"name":"Appointments","description":"Operations related to appointment management"},{"name":"Treatments","description":"Operations related to patient treatment management"},{"name":"Clinic Info","description":"Operations related to clinic information management"},{"name":"Notes","description":"Operations related to patient note management"},{"name":"Financial Summaries","description":"Operations related to patient financial summary management"},{"name":"Invoices","description":"Operations related to invoice and payment management"},{"name":"Patients","description":"Operations related to patient management"},{"name":"Staff","description":"Operations related to staff management"},{"name":"Dental Charts","description":"Operations related to dental chart and tooth condition management"},{"name":"Lab Requests","description":"Operations related to laboratory request management"},{"name":"Documents","description":"Operations related to patient document management"},{"name":"Specialties","description":"Operations related to specialty management"},{"name":"Treatment Materials","description":"Operations related to treatment material management"},{"name":"Procedures","description":"Operations related to dental procedure management"}],"paths":{"/api/v1/treatments/{id}":{"get":{"tags":["Treatments"],"summary":"Get treatment by ID","description":"Retrieves a specific treatment by its UUID.","operationId":"getTreatmentById","parameters":[{"name":"id","in":"path","description":"Treatment UUID","required":true,"schema":{"type":"string","format":"uuid"}}],"responses":{"200":{"description":"Treatment found","content":{"*/*":{"schema":{"$ref":"#/components/schemas/TreatmentLogDto"}}}},"404":{"description":"Treatment not found","content":{"*/*":{"schema":{"$ref":"#/components/schemas/TreatmentLogDto"}}}}}},"put":{"tags":["Treatments"],"summary":"Update treatment","description":"Updates an existing treatment record.","operationId":"updateTreatment","parameters":[{"name":"id","in":"path","description":"Treatment UUID","required":true,"schema":{"type":"string","format":"uuid"}}],"requestBody":{"content":{"application/json":{"schema":{"$ref":"#/components/schemas/TreatmentCreateRequest"}}},"required":true},"responses":{"200":{"description":"Treatment updated","content":{"*/*":{"schema":{"$ref":"#/components/schemas/TreatmentLogDto"}}}},"404":{"description":"Treatment not found","content":{"*/*":{"schema":{"$ref":"#/components/schemas/TreatmentLogDto"}}}},"400":{"description":"Validation error","content":{"*/*":{"schema":{"$ref":"#/components/schemas/TreatmentLogDto"}}}}}},"delete":{"tags":["Treatments"],"summary":"Delete treatment","description":"Deletes a treatment record by its UUID.","operationId":"deleteTreatment","parameters":[{"name":"id","in":"path","description":"Treatment UUID","required":true,"schema":{"type":"string","format":"uuid"}}],"responses":{"204":{"description":"Treatment deleted"},"404":{"description":"Treatment not found"}}}},"/api/v1/treatment-materials/{id}":{"get":{"tags":["Treatment Materials"],"summary":"Get treatment material by ID","description":"Retrieves a specific treatment material by its ID.","operationId":"getTreatmentMaterial","parameters":[{"name":"id","in":"path","description":"Treatment material ID","required":true,"schema":{"type":"string","format":"uuid"}}],"responses":{"200":{"description":"Treatment material found","content":{"*/*":{"schema":{"$ref":"#/components/schemas/TreatmentMaterialDto"}}}},"404":{"description":"Treatment material not found","content":{"*/*":{"schema":{"$ref":"#/components/schemas/TreatmentMaterialDto"}}}}}},"put":{"tags":["Treatment Materials"],"summary":"Update treatment material","description":"Updates an existing treatment material record.","operationId":"updateTreatmentMaterial","parameters":[{"name":"id","in":"path","description":"Treatment material ID","required":true,"schema":{"type":"string","format":"uuid"}}],"requestBody":{"content":{"application/json":{"schema":{"$ref":"#/components/schemas/TreatmentMaterialCreateRequest"}}},"required":true},"responses":{"200":{"description":"Treatment material updated","content":{"*/*":{"schema":{"$ref":"#/components/schemas/TreatmentMaterialDto"}}}},"400":{"description":"Validation error","content":{"*/*":{"schema":{"$ref":"#/components/schemas/TreatmentMaterialDto"}}}},"404":{"description":"Treatment material not found","content":{"*/*":{"schema":{"$ref":"#/components/schemas/TreatmentMaterialDto"}}}}}},"delete":{"tags":["Treatment Materials"],"summary":"Delete treatment material","description":"Deletes a treatment material record.","operationId":"deleteTreatmentMaterial","parameters":[{"name":"id","in":"path","description":"Treatment material ID","required":true,"schema":{"type":"string","format":"uuid"}}],"responses":{"204":{"description":"Treatment material deleted"},"404":{"description":"Treatment material not found"}}}},"/api/v1/staff/{id}":{"get":{"tags":["Staff"],"summary":"Get staff member by ID","description":"Retrieves a staff member by their unique identifier.","operationId":"getStaffById","parameters":[{"name":"id","in":"path","description":"Staff ID","required":true,"schema":{"type":"string","format":"uuid"}}],"responses":{"200":{"description":"Staff member found","content":{"*/*":{"schema":{"$ref":"#/components/schemas/StaffDto"}}}},"404":{"description":"Staff member not found","content":{"*/*":{"schema":{"$ref":"#/components/schemas/StaffDto"}}}}}},"put":{"tags":["Staff"],"summary":"Update staff member","description":"Updates an existing staff member record.","operationId":"updateStaff","parameters":[{"name":"id","in":"path","description":"Staff ID","required":true,"schema":{"type":"string","format":"uuid"}}],"requestBody":{"content":{"application/json":{"schema":{"$ref":"#/components/schemas/StaffUpdateRequest"}}},"required":true},"responses":{"200":{"description":"Staff member updated","content":{"*/*":{"schema":{"$ref":"#/components/schemas/StaffDto"}}}},"404":{"description":"Staff member not found","content":{"*/*":{"schema":{"$ref":"#/components/schemas/StaffDto"}}}},"400":{"description":"Validation error or email already exists","content":{"*/*":{"schema":{"$ref":"#/components/schemas/StaffDto"}}}}}},"delete":{"tags":["Staff"],"summary":"Delete staff member","description":"Deactivates a staff member (soft delete).","operationId":"deleteStaff","parameters":[{"name":"id","in":"path","description":"Staff ID","required":true,"schema":{"type":"string","format":"uuid"}}],"responses":{"204":{"description":"Staff member deactivated"},"404":{"description":"Staff member not found"}}}},"/api/v1/specialties/{id}":{"get":{"tags":["Specialties"],"summary":"Get specialty by ID","description":"Retrieves a specialty by its unique identifier.","operationId":"getSpecialtyById","parameters":[{"name":"id","in":"path","description":"Specialty ID","required":true,"schema":{"type":"string","format":"uuid"}}],"responses":{"200":{"description":"Specialty found","content":{"*/*":{"schema":{"$ref":"#/components/schemas/SpecialtyDto"}}}},"404":{"description":"Specialty not found","content":{"*/*":{"schema":{"$ref":"#/components/schemas/SpecialtyDto"}}}}}},"put":{"tags":["Specialties"],"summary":"Update specialty","description":"Updates an existing specialty record.","operationId":"updateSpecialty","parameters":[{"name":"id","in":"path","description":"Specialty ID","required":true,"schema":{"type":"string","format":"uuid"}}],"requestBody":{"content":{"application/json":{"schema":{"$ref":"#/components/schemas/SpecialtyUpdateRequest"}}},"required":true},"responses":{"200":{"description":"Specialty updated","content":{"*/*":{"schema":{"$ref":"#/components/schemas/SpecialtyDto"}}}},"404":{"description":"Specialty not found","content":{"*/*":{"schema":{"$ref":"#/components/schemas/SpecialtyDto"}}}},"400":{"description":"Validation error or specialty name already exists","content":{"*/*":{"schema":{"$ref":"#/components/schemas/SpecialtyDto"}}}}}},"delete":{"tags":["Specialties"],"summary":"Delete specialty","description":"Deactivates a specialty (soft delete).","operationId":"deleteSpecialty","parameters":[{"name":"id","in":"path","description":"Specialty ID","required":true,"schema":{"type":"string","format":"uuid"}}],"responses":{"204":{"description":"Specialty deactivated"},"404":{"description":"Specialty not found"}}}},"/api/v1/patients/{id}":{"get":{"tags":["Patients"],"summary":"Get patient by ID","description":"Retrieves a patient by their unique identifier.","operationId":"getPatientById","parameters":[{"name":"id","in":"path","description":"Patient ID","required":true,"schema":{"type":"string","format":"uuid"}}],"responses":{"200":{"description":"Patient found","content":{"*/*":{"schema":{"$ref":"#/components/schemas/PatientSummaryDto"}}}},"404":{"description":"Patient not found","content":{"*/*":{"schema":{"$ref":"#/components/schemas/PatientSummaryDto"}}}}}},"put":{"tags":["Patients"],"summary":"Update patient","description":"Updates an existing patient record.","operationId":"updatePatient","parameters":[{"name":"id","in":"path","description":"Patient ID","required":true,"schema":{"type":"string","format":"uuid"}}],"requestBody":{"content":{"application/json":{"schema":{"$ref":"#/components/schemas/PatientUpdateRequest"}}},"required":true},"responses":{"200":{"description":"Patient updated","content":{"*/*":{"schema":{"$ref":"#/components/schemas/PatientSummaryDto"}}}},"404":{"description":"Patient not found","content":{"*/*":{"schema":{"$ref":"#/components/schemas/PatientSummaryDto"}}}},"400":{"description":"Validation error","content":{"*/*":{"schema":{"$ref":"#/components/schemas/PatientSummaryDto"}}}}}},"delete":{"tags":["Patients"],"summary":"Delete patient","description":"Deletes a patient record by setting them as inactive.","operationId":"deletePatient","parameters":[{"name":"id","in":"path","description":"Patient ID","required":true,"schema":{"type":"string","format":"uuid"}}],"responses":{"204":{"description":"Patient deleted"},"404":{"description":"Patient not found"}}}},"/api/v1/notes/{id}":{"get":{"tags":["Notes"],"summary":"Get note by ID","description":"Retrieves a specific note by its UUID.","operationId":"getNoteById","parameters":[{"name":"id","in":"path","description":"Note UUID","required":true,"schema":{"type":"string","format":"uuid"}}],"responses":{"200":{"description":"Note found","content":{"*/*":{"schema":{"$ref":"#/components/schemas/NoteSummaryDto"}}}},"404":{"description":"Note not found","content":{"*/*":{"schema":{"$ref":"#/components/schemas/NoteSummaryDto"}}}}}},"put":{"tags":["Notes"],"summary":"Update note","description":"Updates an existing note by its UUID.","operationId":"updateNote","parameters":[{"name":"id","in":"path","description":"Note UUID","required":true,"schema":{"type":"string","format":"uuid"}}],"requestBody":{"content":{"application/json":{"schema":{"$ref":"#/components/schemas/NoteUpdateRequest"}}},"required":true},"responses":{"200":{"description":"Note updated","content":{"*/*":{"schema":{"$ref":"#/components/schemas/NoteSummaryDto"}}}},"404":{"description":"Note not found","content":{"*/*":{"schema":{"$ref":"#/components/schemas/NoteSummaryDto"}}}},"400":{"description":"Validation error","content":{"*/*":{"schema":{"$ref":"#/components/schemas/NoteSummaryDto"}}}}}},"delete":{"tags":["Notes"],"summary":"Delete note","description":"Deletes a note by its UUID.","operationId":"deleteNote","parameters":[{"name":"id","in":"path","description":"Note UUID","required":true,"schema":{"type":"string","format":"uuid"}}],"responses":{"204":{"description":"Note deleted"},"404":{"description":"Note not found"}}}},"/api/v1/lab-requests/{id}/status":{"put":{"tags":["Lab Requests"],"summary":"Update lab request status","description":"Updates the status of an existing lab request.","operationId":"updateLabRequestStatus","parameters":[{"name":"id","in":"path","description":"Lab request UUID","required":true,"schema":{"type":"string","format":"uuid"}},{"name":"status","in":"query","description":"New status","required":true,"schema":{"type":"string"}}],"responses":{"200":{"description":"Lab request status updated","content":{"*/*":{"schema":{"$ref":"#/components/schemas/LabRequestDto"}}}},"404":{"description":"Lab request not found","content":{"*/*":{"schema":{"$ref":"#/components/schemas/LabRequestDto"}}}},"400":{"description":"Validation error","content":{"*/*":{"schema":{"$ref":"#/components/schemas/LabRequestDto"}}}}}}},"/api/v1/dental-charts/patient/{patientId}/tooth/{toothNumber}":{"get":{"tags":["Dental Charts"],"summary":"Get tooth details","description":"Retrieves detailed information for a specific tooth of a patient.","operationId":"getToothDetails","parameters":[{"name":"patientId","in":"path","description":"Patient UUID","required":true,"schema":{"type":"string","format":"uuid"}},{"name":"toothNumber","in":"path","description":"Tooth number (1-32)","required":true,"schema":{"type":"integer","format":"int32"}}],"responses":{"200":{"description":"Tooth details retrieved","content":{"*/*":{"schema":{"$ref":"#/components/schemas/ToothDto"}}}},"404":{"description":"Patient or tooth not found","content":{"*/*":{"schema":{"$ref":"#/components/schemas/ToothDto"}}}}}},"put":{"tags":["Dental Charts"],"summary":"Update tooth condition","description":"Updates the condition and notes for a specific tooth of a patient.","operationId":"updateToothCondition","parameters":[{"name":"patientId","in":"path","description":"Patient UUID","required":true,"schema":{"type":"string","format":"uuid"}},{"name":"toothNumber","in":"path","description":"Tooth number (1-32)","required":true,"schema":{"type":"integer","format":"int32"}},{"name":"conditionId","in":"query","description":"Tooth condition UUID","required":true,"schema":{"type":"string","format":"uuid"}},{"name":"notes","in":"query","description":"Additional notes about the tooth condition","required":false,"schema":{"type":"string"}}],"responses":{"200":{"description":"Tooth condition updated","content":{"*/*":{"schema":{"$ref":"#/components/schemas/ToothDto"}}}},"404":{"description":"Patient or tooth not found","content":{"*/*":{"schema":{"$ref":"#/components/schemas/ToothDto"}}}},"400":{"description":"Invalid tooth number or condition","content":{"*/*":{"schema":{"$ref":"#/components/schemas/ToothDto"}}}}}}},"/api/v1/clinic-info":{"get":{"tags":["Clinic Info"],"summary":"Get clinic information","description":"Retrieves the clinic information.","operationId":"getClinicInfo","responses":{"200":{"description":"Clinic information retrieved","content":{"*/*":{"schema":{"$ref":"#/components/schemas/ClinicInfoDto"}}}},"404":{"description":"Clinic information not found","content":{"*/*":{"schema":{"$ref":"#/components/schemas/ClinicInfoDto"}}}}}},"put":{"tags":["Clinic Info"],"summary":"Update clinic information","description":"Updates the clinic information.","operationId":"updateClinicInfo","requestBody":{"content":{"application/json":{"schema":{"$ref":"#/components/schemas/ClinicInfoUpdateRequest"}}},"required":true},"responses":{"200":{"description":"Clinic information updated","content":{"*/*":{"schema":{"$ref":"#/components/schemas/ClinicInfoDto"}}}},"400":{"description":"Validation error","content":{"*/*":{"schema":{"$ref":"#/components/schemas/ClinicInfoDto"}}}},"404":{"description":"Clinic information not found","content":{"*/*":{"schema":{"$ref":"#/components/schemas/ClinicInfoDto"}}}}}}},"/api/v1/treatments":{"post":{"tags":["Treatments"],"summary":"Create new treatment","description":"Creates a new treatment record for a patient.","operationId":"createTreatment","parameters":[{"name":"patientId","in":"query","description":"Patient UUID","required":true,"schema":{"type":"string","format":"uuid"}}],"requestBody":{"content":{"application/json":{"schema":{"$ref":"#/components/schemas/TreatmentCreateRequest"}}},"required":true},"responses":{"201":{"description":"Treatment created","content":{"*/*":{"schema":{"$ref":"#/components/schemas/TreatmentLogDto"}}}},"400":{"description":"Validation error","content":{"*/*":{"schema":{"$ref":"#/components/schemas/TreatmentLogDto"}}}},"404":{"description":"Patient or procedure not found","content":{"*/*":{"schema":{"$ref":"#/components/schemas/TreatmentLogDto"}}}}}}},"/api/v1/treatments/search":{"post":{"tags":["Treatments"],"summary":"Advanced treatment search","description":"Search treatments with multiple criteria and filters.","operationId":"searchTreatments","parameters":[{"name":"page","in":"query","description":"Zero-based page index (0..N)","example":0},{"name":"size","in":"query","description":"The size of the page to be returned","example":20},{"name":"sort","in":"query","description":"Sorting criteria: property(,asc|desc). Default: treatmentDate","example":"treatmentDate"}],"requestBody":{"content":{"application/json":{"schema":{"$ref":"#/components/schemas/TreatmentSearchCriteria"}}},"required":true},"responses":{"200":{"description":"Treatments retrieved","content":{"*/*":{"schema":{"$ref":"#/components/schemas/PageTreatmentLogDto"}}}}}}},"/api/v1/treatment-materials":{"post":{"tags":["Treatment Materials"],"summary":"Create treatment material record","description":"Creates a new treatment material record.","operationId":"createTreatmentMaterial","requestBody":{"content":{"application/json":{"schema":{"$ref":"#/components/schemas/TreatmentMaterialCreateRequest"}}},"required":true},"responses":{"201":{"description":"Treatment material created","content":{"*/*":{"schema":{"$ref":"#/components/schemas/TreatmentMaterialDto"}}}},"400":{"description":"Validation error","content":{"*/*":{"schema":{"$ref":"#/components/schemas/TreatmentMaterialDto"}}}},"404":{"description":"Treatment not found","content":{"*/*":{"schema":{"$ref":"#/components/schemas/TreatmentMaterialDto"}}}}}}},"/api/v1/treatment-materials/search":{"post":{"tags":["Treatment Materials"],"summary":"Advanced material search","description":"Search treatment materials with multiple criteria and filters.","operationId":"searchMaterials","parameters":[{"name":"page","in":"query","description":"Zero-based page index (0..N)","example":0},{"name":"size","in":"query","description":"The size of the page to be returned","example":20},{"name":"sort","in":"query","description":"Sorting criteria: property(,asc|desc). Default: createdAt","example":"createdAt"}],"requestBody":{"content":{"application/json":{"schema":{"$ref":"#/components/schemas/TreatmentMaterialSearchCriteria"}}},"required":true},"responses":{"200":{"description":"Materials retrieved","content":{"*/*":{"schema":{"$ref":"#/components/schemas/PageTreatmentMaterialDto"}}}}}}},"/api/v1/staff":{"get":{"tags":["Staff"],"summary":"Get all staff members","description":"Retrieves paginated list of all staff members.","operationId":"getAllStaff","parameters":[{"name":"page","in":"query","description":"Zero-based page index (0..N)","example":0},{"name":"size","in":"query","description":"The size of the page to be returned","example":20},{"name":"sort","in":"query","description":"Sorting criteria: property(,asc|desc). Default: fullName","example":"fullName"}],"responses":{"200":{"description":"Staff members retrieved","content":{"*/*":{"schema":{"$ref":"#/components/schemas/PageStaffDto"}}}}}},"post":{"tags":["Staff"],"summary":"Create new staff member","description":"Creates a new staff member record.","operationId":"createStaff","requestBody":{"content":{"application/json":{"schema":{"$ref":"#/components/schemas/StaffCreateRequest"}}},"required":true},"responses":{"201":{"description":"Staff member created","content":{"*/*":{"schema":{"$ref":"#/components/schemas/StaffDto"}}}},"400":{"description":"Validation error or email already exists","content":{"*/*":{"schema":{"$ref":"#/components/schemas/StaffDto"}}}}}}},"/api/v1/staff/search/advanced":{"post":{"tags":["Staff"],"summary":"Advanced staff search","description":"Search staff members with multiple criteria and filters.","operationId":"advancedSearchStaff","parameters":[{"name":"page","in":"query","description":"Zero-based page index (0..N)","example":0},{"name":"size","in":"query","description":"The size of the page to be returned","example":20},{"name":"sort","in":"query","description":"Sorting criteria: property(,asc|desc). Default: fullName","example":"fullName"}],"requestBody":{"content":{"application/json":{"schema":{"$ref":"#/components/schemas/StaffSearchCriteria"}}},"required":true},"responses":{"200":{"description":"Staff members retrieved","content":{"*/*":{"schema":{"$ref":"#/components/schemas/PageStaffDto"}}}}}}},"/api/v1/specialties":{"get":{"tags":["Specialties"],"summary":"Get all specialties","description":"Retrieves paginated list of all specialties.","operationId":"getAllSpecialties","parameters":[{"name":"page","in":"query","description":"Zero-based page index (0..N)","example":0},{"name":"size","in":"query","description":"The size of the page to be returned","example":20},{"name":"sort","in":"query","description":"Sorting criteria: property(,asc|desc). Default: name","example":"name"}],"responses":{"200":{"description":"Specialties retrieved","content":{"*/*":{"schema":{"$ref":"#/components/schemas/PageSpecialtyDto"}}}}}},"post":{"tags":["Specialties"],"summary":"Create new specialty","description":"Creates a new specialty record.","operationId":"createSpecialty","requestBody":{"content":{"application/json":{"schema":{"$ref":"#/components/schemas/SpecialtyCreateRequest"}}},"required":true},"responses":{"201":{"description":"Specialty created","content":{"*/*":{"schema":{"$ref":"#/components/schemas/SpecialtyDto"}}}},"400":{"description":"Validation error or specialty already exists","content":{"*/*":{"schema":{"$ref":"#/components/schemas/SpecialtyDto"}}}}}}},"/api/v1/patients":{"get":{"tags":["Patients"],"summary":"Get all patients","description":"Retrieves paginated list of patients with optional search filtering.","operationId":"getAllPatients","parameters":[{"name":"page","in":"query","description":"Zero-based page index (0..N)","example":0},{"name":"size","in":"query","description":"The size of the page to be returned","example":20},{"name":"sort","in":"query","description":"Sorting criteria: property(,asc|desc). Default: fullName","example":"fullName"},{"name":"searchTerm","in":"query","description":"Search term for filtering patients","required":false,"schema":{"type":"string"}}],"responses":{"200":{"description":"Patients retrieved","content":{"*/*":{"schema":{"$ref":"#/components/schemas/PagePatientSummaryDto"}}}}}},"post":{"tags":["Patients"],"summary":"Create new patient","description":"Creates a new patient record in the system.","operationId":"createPatient","requestBody":{"content":{"application/json":{"schema":{"$ref":"#/components/schemas/PatientCreateRequest"}}},"required":true},"responses":{"201":{"description":"Patient created","content":{"*/*":{"schema":{"$ref":"#/components/schemas/PatientSummaryDto"}}}},"400":{"description":"Validation error","content":{"*/*":{"schema":{"$ref":"#/components/schemas/PatientSummaryDto"}}}}}}},"/api/v1/patients/search":{"post":{"tags":["Patients"],"summary":"Advanced patient search","description":"Search patients with multiple criteria and filters.","operationId":"searchPatients","parameters":[{"name":"page","in":"query","description":"Zero-based page index (0..N)","example":0},{"name":"size","in":"query","description":"The size of the page to be returned","example":20},{"name":"sort","in":"query","description":"Sorting criteria: property(,asc|desc). Default: fullName","example":"fullName"}],"requestBody":{"content":{"application/json":{"schema":{"$ref":"#/components/schemas/PatientSearchCriteria"}}},"required":true},"responses":{"200":{"description":"Patients retrieved","content":{"*/*":{"schema":{"$ref":"#/components/schemas/PagePatientSummaryDto"}}}}}}},"/api/v1/notes":{"post":{"tags":["Notes"],"summary":"Create new note","description":"Creates a new note for a patient.","operationId":"createNote","requestBody":{"content":{"application/json":{"schema":{"$ref":"#/components/schemas/NoteCreateRequest"}}},"required":true},"responses":{"201":{"description":"Note created","content":{"*/*":{"schema":{"$ref":"#/components/schemas/NoteSummaryDto"}}}},"400":{"description":"Validation error","content":{"*/*":{"schema":{"$ref":"#/components/schemas/NoteSummaryDto"}}}},"404":{"description":"Patient not found","content":{"*/*":{"schema":{"$ref":"#/components/schemas/NoteSummaryDto"}}}}}}},"/api/v1/lab-requests":{"post":{"tags":["Lab Requests"],"summary":"Create new lab request","description":"Creates a new laboratory request for a patient.","operationId":"createLabRequest","requestBody":{"content":{"application/json":{"schema":{"$ref":"#/components/schemas/LabRequestCreateRequest"}}},"required":true},"responses":{"201":{"description":"Lab request created","content":{"*/*":{"schema":{"$ref":"#/components/schemas/LabRequestDto"}}}},"400":{"description":"Validation error","content":{"*/*":{"schema":{"$ref":"#/components/schemas/LabRequestDto"}}}},"404":{"description":"Patient not found","content":{"*/*":{"schema":{"$ref":"#/components/schemas/LabRequestDto"}}}}}}},"/api/v1/invoices":{"post":{"tags":["Invoices"],"summary":"Create new invoice","description":"Creates a new invoice for a patient with auto-generated invoice number.","operationId":"createInvoice","requestBody":{"content":{"application/json":{"schema":{"$ref":"#/components/schemas/InvoiceCreateRequest"}}},"required":true},"responses":{"201":{"description":"Invoice created","content":{"*/*":{"schema":{"$ref":"#/components/schemas/FinancialRecordDto"}}}},"400":{"description":"Validation error","content":{"*/*":{"schema":{"$ref":"#/components/schemas/FinancialRecordDto"}}}},"404":{"description":"Patient not found","content":{"*/*":{"schema":{"$ref":"#/components/schemas/FinancialRecordDto"}}}}}}},"/api/v1/invoices/{invoiceId}/payments":{"post":{"tags":["Invoices"],"summary":"Add payment to invoice","description":"Records a payment against an existing invoice and updates patient balance.","operationId":"addPayment","parameters":[{"name":"invoiceId","in":"path","description":"Invoice UUID","required":true,"schema":{"type":"string","format":"uuid"}}],"requestBody":{"content":{"application/json":{"schema":{"$ref":"#/components/schemas/PaymentCreateRequest"}}},"required":true},"responses":{"201":{"description":"Payment recorded","content":{"*/*":{"schema":{"$ref":"#/components/schemas/FinancialRecordDto"}}}},"400":{"description":"Validation error","content":{"*/*":{"schema":{"$ref":"#/components/schemas/FinancialRecordDto"}}}},"404":{"description":"Invoice not found","content":{"*/*":{"schema":{"$ref":"#/components/schemas/FinancialRecordDto"}}}}}}},"/api/v1/invoices/patient/{patientId}/recalculate-balance":{"post":{"tags":["Invoices"],"summary":"Recalculate patient balance","description":"Manually recalculates patient balance based on all invoices and payments.","operationId":"recalculatePatientBalance","parameters":[{"name":"patientId","in":"path","description":"Patient UUID","required":true,"schema":{"type":"string","format":"uuid"}}],"responses":{"200":{"description":"Balance recalculated","content":{"*/*":{"schema":{"type":"number"}}}},"404":{"description":"Patient not found","content":{"*/*":{"schema":{"type":"number"}}}}}}},"/api/v1/appointments":{"post":{"tags":["Appointments"],"summary":"Create new appointment","description":"Creates a new appointment in the system.","operationId":"createAppointment","requestBody":{"content":{"application/json":{"schema":{"$ref":"#/components/schemas/AppointmentCreateRequest"}}},"required":true},"responses":{"201":{"description":"Appointment created","content":{"*/*":{"schema":{"$ref":"#/components/schemas/AppointmentCardDto"}}}},"400":{"description":"Validation error","content":{"*/*":{"schema":{"$ref":"#/components/schemas/AppointmentCardDto"}}}}}}},"/api/v1/treatments/patient/{patientId}":{"get":{"tags":["Treatments"],"summary":"Get patient treatment history","description":"Retrieves paginated treatment history for a specific patient.","operationId":"getPatientTreatmentHistory","parameters":[{"name":"page","in":"query","description":"Zero-based page index (0..N)","example":0},{"name":"size","in":"query","description":"The size of the page to be returned","example":20},{"name":"sort","in":"query","description":"Sorting criteria: property(,asc|desc). Default: treatmentDate","example":"treatmentDate"},{"name":"patientId","in":"path","description":"Patient UUID","required":true,"schema":{"type":"string","format":"uuid"}}],"responses":{"200":{"description":"Treatment history retrieved","content":{"*/*":{"schema":{"$ref":"#/components/schemas/PageTreatmentLogDto"}}}},"404":{"description":"Patient not found","content":{"*/*":{"schema":{"$ref":"#/components/schemas/PageTreatmentLogDto"}}}}}}},"/api/v1/treatment-materials/treatment/{treatmentId}":{"get":{"tags":["Treatment Materials"],"summary":"Get materials by treatment ID","description":"Retrieves all materials used in a specific treatment.","operationId":"getMaterialsByTreatment","parameters":[{"name":"treatmentId","in":"path","description":"Treatment ID","required":true,"schema":{"type":"string","format":"uuid"}}],"responses":{"200":{"description":"Materials retrieved","content":{"*/*":{"schema":{"type":"array","items":{"$ref":"#/components/schemas/TreatmentMaterialDto"}}}}}}}},"/api/v1/treatment-materials/treatment/{treatmentId}/total-cost":{"get":{"tags":["Treatment Materials"],"summary":"Get total material cost for treatment","description":"Calculates the total cost of materials used in a treatment.","operationId":"getTotalMaterialCostByTreatment","parameters":[{"name":"treatmentId","in":"path","description":"Treatment ID","required":true,"schema":{"type":"string","format":"uuid"}}],"responses":{"200":{"description":"Total cost calculated","content":{"*/*":{"schema":{"type":"number"}}}}}}},"/api/v1/treatment-materials/treatment/{treatmentId}/paged":{"get":{"tags":["Treatment Materials"],"summary":"Get materials by treatment ID (paginated)","description":"Retrieves materials used in a specific treatment with pagination.","operationId":"getMaterialsByTreatmentPaged","parameters":[{"name":"page","in":"query","description":"Zero-based page index (0..N)","example":0},{"name":"size","in":"query","description":"The size of the page to be returned","example":20},{"name":"sort","in":"query","description":"Sorting criteria: property(,asc|desc). Default: createdAt","example":"createdAt"},{"name":"treatmentId","in":"path","description":"Treatment ID","required":true,"schema":{"type":"string","format":"uuid"}}],"responses":{"200":{"description":"Materials retrieved","content":{"*/*":{"schema":{"$ref":"#/components/schemas/PageTreatmentMaterialDto"}}}}}}},"/api/v1/treatment-materials/patient/{patientId}":{"get":{"tags":["Treatment Materials"],"summary":"Get materials by patient ID","description":"Retrieves all materials used for a specific patient.","operationId":"getMaterialsByPatient","parameters":[{"name":"patientId","in":"path","description":"Patient ID","required":true,"schema":{"type":"string","format":"uuid"}}],"responses":{"200":{"description":"Materials retrieved","content":{"*/*":{"schema":{"type":"array","items":{"$ref":"#/components/schemas/TreatmentMaterialDto"}}}}}}}},"/api/v1/treatment-materials/patient/{patientId}/total-cost":{"get":{"tags":["Treatment Materials"],"summary":"Get total material cost for patient","description":"Calculates the total cost of materials used for a patient.","operationId":"getTotalMaterialCostByPatient","parameters":[{"name":"patientId","in":"path","description":"Patient ID","required":true,"schema":{"type":"string","format":"uuid"}}],"responses":{"200":{"description":"Total cost calculated","content":{"*/*":{"schema":{"type":"number"}}}}}}},"/api/v1/treatment-materials/patient/{patientId}/paged":{"get":{"tags":["Treatment Materials"],"summary":"Get materials by patient ID (paginated)","description":"Retrieves materials used for a specific patient with pagination.","operationId":"getMaterialsByPatientPaged","parameters":[{"name":"page","in":"query","description":"Zero-based page index (0..N)","example":0},{"name":"size","in":"query","description":"The size of the page to be returned","example":20},{"name":"sort","in":"query","description":"Sorting criteria: property(,asc|desc). Default: createdAt","example":"createdAt"},{"name":"patientId","in":"path","description":"Patient ID","required":true,"schema":{"type":"string","format":"uuid"}}],"responses":{"200":{"description":"Materials retrieved","content":{"*/*":{"schema":{"$ref":"#/components/schemas/PageTreatmentMaterialDto"}}}}}}},"/api/v1/staff/search":{"get":{"tags":["Staff"],"summary":"Search staff members","description":"Search staff members by name, email, or phone number.","operationId":"searchStaff","parameters":[{"name":"page","in":"query","description":"Zero-based page index (0..N)","example":0},{"name":"size","in":"query","description":"The size of the page to be returned","example":20},{"name":"sort","in":"query","description":"Sorting criteria: property(,asc|desc). Default: fullName","example":"fullName"},{"name":"searchTerm","in":"query","description":"Search term for filtering staff members","required":false,"schema":{"type":"string"}}],"responses":{"200":{"description":"Staff members retrieved","content":{"*/*":{"schema":{"$ref":"#/components/schemas/PageStaffDto"}}}}}}},"/api/v1/staff/by-role/{role}":{"get":{"tags":["Staff"],"summary":"Get staff members by role","description":"Retrieves paginated list of staff members with a specific role.","operationId":"getStaffByRole","parameters":[{"name":"page","in":"query","description":"Zero-based page index (0..N)","example":0},{"name":"size","in":"query","description":"The size of the page to be returned","example":20},{"name":"sort","in":"query","description":"Sorting criteria: property(,asc|desc). Default: fullName","example":"fullName"},{"name":"role","in":"path","description":"Staff role","required":true,"schema":{"type":"string","enum":["DOCTOR","NURSE","ASSISTANT","RECEPTIONIST","ACCOUNTANT","ADMIN"]}}],"responses":{"200":{"description":"Staff members retrieved","content":{"*/*":{"schema":{"$ref":"#/components/schemas/PageStaffDto"}}}}}}},"/api/v1/staff/active":{"get":{"tags":["Staff"],"summary":"Get active staff members","description":"Retrieves paginated list of active staff members.","operationId":"getActiveStaff","parameters":[{"name":"page","in":"query","description":"Zero-based page index (0..N)","example":0},{"name":"size","in":"query","description":"The size of the page to be returned","example":20},{"name":"sort","in":"query","description":"Sorting criteria: property(,asc|desc). Default: fullName","example":"fullName"}],"responses":{"200":{"description":"Active staff members retrieved","content":{"*/*":{"schema":{"$ref":"#/components/schemas/PageStaffDto"}}}}}}},"/api/v1/specialties/search":{"get":{"tags":["Specialties"],"summary":"Search specialties","description":"Search specialties by name or description.","operationId":"searchSpecialties","parameters":[{"name":"page","in":"query","description":"Zero-based page index (0..N)","example":0},{"name":"size","in":"query","description":"The size of the page to be returned","example":20},{"name":"sort","in":"query","description":"Sorting criteria: property(,asc|desc). Default: name","example":"name"},{"name":"searchTerm","in":"query","description":"Search term for filtering specialties","required":false,"schema":{"type":"string"}}],"responses":{"200":{"description":"Specialties retrieved","content":{"*/*":{"schema":{"$ref":"#/components/schemas/PageSpecialtyDto"}}}}}}},"/api/v1/specialties/active":{"get":{"tags":["Specialties"],"summary":"Get active specialties","description":"Retrieves paginated list of active specialties.","operationId":"getActiveSpecialties","parameters":[{"name":"page","in":"query","description":"Zero-based page index (0..N)","example":0},{"name":"size","in":"query","description":"The size of the page to be returned","example":20},{"name":"sort","in":"query","description":"Sorting criteria: property(,asc|desc). Default: name","example":"name"}],"responses":{"200":{"description":"Active specialties retrieved","content":{"*/*":{"schema":{"$ref":"#/components/schemas/PageSpecialtyDto"}}}}}}},"/api/v1/procedures":{"get":{"tags":["Procedures"],"summary":"Get all procedures","description":"Retrieves paginated list of all available dental procedures.","operationId":"getAllProcedures","parameters":[{"name":"page","in":"query","description":"Zero-based page index (0..N)","example":0},{"name":"size","in":"query","description":"The size of the page to be returned","example":20},{"name":"sort","in":"query","description":"Sorting criteria: property(,asc|desc). Default: name","example":"name"}],"responses":{"200":{"description":"Procedures retrieved","content":{"*/*":{"schema":{"$ref":"#/components/schemas/PageProcedureSummaryDto"}}}}}}},"/api/v1/procedures/{id}":{"get":{"tags":["Procedures"],"summary":"Get procedure by ID","description":"Retrieves a specific procedure by its UUID.","operationId":"getProcedureById","parameters":[{"name":"id","in":"path","description":"Procedure UUID","required":true,"schema":{"type":"string","format":"uuid"}}],"responses":{"200":{"description":"Procedure found","content":{"*/*":{"schema":{"$ref":"#/components/schemas/ProcedureSummaryDto"}}}},"404":{"description":"Procedure not found","content":{"*/*":{"schema":{"$ref":"#/components/schemas/ProcedureSummaryDto"}}}}}}},"/api/v1/procedures/search":{"get":{"tags":["Procedures"],"summary":"Search procedures","description":"Searches procedures by name or description.","operationId":"searchProcedures","parameters":[{"name":"searchTerm","in":"query","description":"Search term for procedure name or description","required":false,"schema":{"type":"string"}}],"responses":{"200":{"description":"Search results retrieved","content":{"*/*":{"schema":{"type":"array","items":{"$ref":"#/components/schemas/ProcedureSummaryDto"}}}}}}}},"/api/v1/procedures/active":{"get":{"tags":["Procedures"],"summary":"Get active procedures","description":"Retrieves list of all active dental procedures.","operationId":"getActiveProcedures","responses":{"200":{"description":"Active procedures retrieved","content":{"*/*":{"schema":{"type":"array","items":{"$ref":"#/components/schemas/ProcedureSummaryDto"}}}}}}}},"/api/v1/patients/{id}/treatments":{"get":{"tags":["Patients"],"summary":"Get patient treatment history","description":"Retrieves paginated treatment history for a specific patient.","operationId":"getPatientTreatmentHistory_1","parameters":[{"name":"page","in":"query","description":"Zero-based page index (0..N)","example":0},{"name":"size","in":"query","description":"The size of the page to be returned","example":20},{"name":"sort","in":"query","description":"Sorting criteria: property(,asc|desc). Default: treatmentDate","example":"treatmentDate"},{"name":"id","in":"path","description":"Patient ID","required":true,"schema":{"type":"string","format":"uuid"}}],"responses":{"200":{"description":"Treatment history retrieved","content":{"*/*":{"schema":{"$ref":"#/components/schemas/PageTreatmentLogDto"}}}},"404":{"description":"Patient not found","content":{"*/*":{"schema":{"$ref":"#/components/schemas/PageTreatmentLogDto"}}}}}}},"/api/v1/patients/{id}/notes":{"get":{"tags":["Patients"],"summary":"Get patient notes","description":"Retrieves paginated list of notes for a specific patient.","operationId":"getPatientNotes","parameters":[{"name":"page","in":"query","description":"Zero-based page index (0..N)","example":0},{"name":"size","in":"query","description":"The size of the page to be returned","example":20},{"name":"sort","in":"query","description":"Sorting criteria: property(,asc|desc). Default: createdAt","example":"createdAt"},{"name":"id","in":"path","description":"Patient ID","required":true,"schema":{"type":"string","format":"uuid"}}],"responses":{"200":{"description":"Notes retrieved","content":{"*/*":{"schema":{"$ref":"#/components/schemas/PageNoteSummaryDto"}}}},"404":{"description":"Patient not found","content":{"*/*":{"schema":{"$ref":"#/components/schemas/PageNoteSummaryDto"}}}}}}},"/api/v1/patients/{id}/lab-requests":{"get":{"tags":["Patients"],"summary":"Get patient lab requests","description":"Retrieves paginated list of lab requests for a specific patient.","operationId":"getPatientLabRequests","parameters":[{"name":"page","in":"query","description":"Zero-based page index (0..N)","example":0},{"name":"size","in":"query","description":"The size of the page to be returned","example":20},{"name":"sort","in":"query","description":"Sorting criteria: property(,asc|desc). Default: requestDate","example":"requestDate"},{"name":"id","in":"path","description":"Patient ID","required":true,"schema":{"type":"string","format":"uuid"}}],"responses":{"200":{"description":"Lab requests retrieved","content":{"*/*":{"schema":{"$ref":"#/components/schemas/PageLabRequestDto"}}}},"404":{"description":"Patient not found","content":{"*/*":{"schema":{"$ref":"#/components/schemas/PageLabRequestDto"}}}}}}},"/api/v1/patients/{id}/financial-records":{"get":{"tags":["Patients"],"summary":"Get patient financial records","description":"Retrieves paginated financial records for a specific patient.","operationId":"getPatientFinancialRecords","parameters":[{"name":"page","in":"query","description":"Zero-based page index (0..N)","example":0},{"name":"size","in":"query","description":"The size of the page to be returned","example":20},{"name":"sort","in":"query","description":"Sorting criteria: property(,asc|desc). Default: invoiceDate","example":"invoiceDate"},{"name":"id","in":"path","description":"Patient ID","required":true,"schema":{"type":"string","format":"uuid"}}],"responses":{"200":{"description":"Financial records retrieved","content":{"*/*":{"schema":{"$ref":"#/components/schemas/PageFinancialRecordDto"}}}},"404":{"description":"Patient not found","content":{"*/*":{"schema":{"$ref":"#/components/schemas/PageFinancialRecordDto"}}}}}}},"/api/v1/patients/{id}/documents":{"get":{"tags":["Patients"],"summary":"Get patient documents","description":"Retrieves paginated list of documents for a specific patient.","operationId":"getPatientDocuments","parameters":[{"name":"page","in":"query","description":"Zero-based page index (0..N)","example":0},{"name":"size","in":"query","description":"The size of the page to be returned","example":20},{"name":"sort","in":"query","description":"Sorting criteria: property(,asc|desc). Default: createdAt","example":"createdAt"},{"name":"id","in":"path","description":"Patient ID","required":true,"schema":{"type":"string","format":"uuid"}}],"responses":{"200":{"description":"Documents retrieved","content":{"*/*":{"schema":{"$ref":"#/components/schemas/PageDocumentSummaryDto"}}}},"404":{"description":"Patient not found","content":{"*/*":{"schema":{"$ref":"#/components/schemas/PageDocumentSummaryDto"}}}}}}},"/api/v1/notes/patient/{patientId}":{"get":{"tags":["Notes"],"summary":"Get patient notes","description":"Retrieves paginated list of notes for a specific patient.","operationId":"getPatientNotes_1","parameters":[{"name":"page","in":"query","description":"Zero-based page index (0..N)","example":0},{"name":"size","in":"query","description":"The size of the page to be returned","example":20},{"name":"sort","in":"query","description":"Sorting criteria: property(,asc|desc). Default: createdAt","example":"createdAt"},{"name":"patientId","in":"path","description":"Patient UUID","required":true,"schema":{"type":"string","format":"uuid"}}],"responses":{"200":{"description":"Notes retrieved","content":{"*/*":{"schema":{"$ref":"#/components/schemas/PageNoteSummaryDto"}}}},"404":{"description":"Patient not found","content":{"*/*":{"schema":{"$ref":"#/components/schemas/PageNoteSummaryDto"}}}}}}},"/api/v1/lab-requests/{id}":{"get":{"tags":["Lab Requests"],"summary":"Get lab request by ID","description":"Retrieves a specific lab request by its UUID.","operationId":"getLabRequestById","parameters":[{"name":"id","in":"path","description":"Lab request UUID","required":true,"schema":{"type":"string","format":"uuid"}}],"responses":{"200":{"description":"Lab request found","content":{"*/*":{"schema":{"$ref":"#/components/schemas/LabRequestDto"}}}},"404":{"description":"Lab request not found","content":{"*/*":{"schema":{"$ref":"#/components/schemas/LabRequestDto"}}}}}}},"/api/v1/lab-requests/patient/{patientId}":{"get":{"tags":["Lab Requests"],"summary":"Get patient lab requests","description":"Retrieves paginated list of lab requests for a specific patient.","operationId":"getPatientLabRequests_1","parameters":[{"name":"page","in":"query","description":"Zero-based page index (0..N)","example":0},{"name":"size","in":"query","description":"The size of the page to be returned","example":20},{"name":"sort","in":"query","description":"Sorting criteria: property(,asc|desc). Default: requestDate","example":"requestDate"},{"name":"patientId","in":"path","description":"Patient UUID","required":true,"schema":{"type":"string","format":"uuid"}}],"responses":{"200":{"description":"Lab requests retrieved","content":{"*/*":{"schema":{"$ref":"#/components/schemas/PageLabRequestDto"}}}},"404":{"description":"Patient not found","content":{"*/*":{"schema":{"$ref":"#/components/schemas/PageLabRequestDto"}}}}}}},"/api/v1/invoices/patient/{patientId}":{"get":{"tags":["Invoices"],"summary":"Get patient financial records","description":"Retrieves paginated financial records (invoices and payments) for a patient.","operationId":"getPatientFinancialRecords_1","parameters":[{"name":"page","in":"query","description":"Zero-based page index (0..N)","example":0},{"name":"size","in":"query","description":"The size of the page to be returned","example":20},{"name":"sort","in":"query","description":"Sorting criteria: property(,asc|desc). Default: invoiceDate","example":"invoiceDate"},{"name":"patientId","in":"path","description":"Patient UUID","required":true,"schema":{"type":"string","format":"uuid"}}],"responses":{"200":{"description":"Financial records retrieved","content":{"*/*":{"schema":{"$ref":"#/components/schemas/PageFinancialRecordDto"}}}},"404":{"description":"Patient not found","content":{"*/*":{"schema":{"$ref":"#/components/schemas/PageFinancialRecordDto"}}}}}}},"/api/v1/invoices/next-invoice-number":{"get":{"tags":["Invoices"],"summary":"Get next invoice number","description":"Retrieves the next sequential invoice number for preview purposes.","operationId":"getNextInvoiceNumber","responses":{"200":{"description":"Next invoice number retrieved","content":{"*/*":{"schema":{"type":"string"}}}}}}},"/api/v1/financial-summaries/patient/{patientId}":{"get":{"tags":["Financial Summaries"],"summary":"Get patient financial summary","description":"Retrieves financial summary for a patient including balance information.","operationId":"getPatientFinancialSummary","parameters":[{"name":"patientId","in":"path","description":"Patient UUID","required":true,"schema":{"type":"string","format":"uuid"}}],"responses":{"200":{"description":"Financial summary retrieved","content":{"*/*":{"schema":{"$ref":"#/components/schemas/PatientBalanceSummaryDto"}}}},"404":{"description":"Patient not found","content":{"*/*":{"schema":{"$ref":"#/components/schemas/PatientBalanceSummaryDto"}}}}}}},"/api/v1/financial-summaries/outstanding-balances":{"get":{"tags":["Financial Summaries"],"summary":"Get patients with outstanding balances","description":"Retrieves financial summaries for patients with outstanding balances.","operationId":"getPatientsWithOutstandingBalances","responses":{"200":{"description":"Outstanding balances retrieved","content":{"*/*":{"schema":{"type":"array","items":{"$ref":"#/components/schemas/PatientFinancialSummaryView"}}}}}}}},"/api/v1/financial-summaries/all":{"get":{"tags":["Financial Summaries"],"summary":"Get all patient financial summaries","description":"Retrieves financial summaries for all patients (for reports).","operationId":"getAllPatientFinancialSummaries","responses":{"200":{"description":"Financial summaries retrieved","content":{"*/*":{"schema":{"type":"array","items":{"$ref":"#/components/schemas/PatientFinancialSummaryView"}}}}}}}},"/api/v1/documents/{id}":{"get":{"tags":["Documents"],"summary":"Get document by ID","description":"Retrieves a specific document by its UUID.","operationId":"getDocumentById","parameters":[{"name":"id","in":"path","description":"Document UUID","required":true,"schema":{"type":"string","format":"uuid"}}],"responses":{"200":{"description":"Document found","content":{"*/*":{"schema":{"$ref":"#/components/schemas/DocumentSummaryDto"}}}},"404":{"description":"Document not found","content":{"*/*":{"schema":{"$ref":"#/components/schemas/DocumentSummaryDto"}}}}}},"delete":{"tags":["Documents"],"summary":"Delete document","description":"Deletes a document by its UUID.","operationId":"deleteDocument","parameters":[{"name":"id","in":"path","description":"Document UUID","required":true,"schema":{"type":"string","format":"uuid"}}],"responses":{"204":{"description":"Document deleted"},"404":{"description":"Document not found"}}}},"/api/v1/documents/patient/{patientId}":{"get":{"tags":["Documents"],"summary":"Get patient documents","description":"Retrieves paginated list of documents for a specific patient.","operationId":"getPatientDocuments_1","parameters":[{"name":"page","in":"query","description":"Zero-based page index (0..N)","example":0},{"name":"size","in":"query","description":"The size of the page to be returned","example":20},{"name":"sort","in":"query","description":"Sorting criteria: property(,asc|desc). Default: createdAt","example":"createdAt"},{"name":"patientId","in":"path","description":"Patient UUID","required":true,"schema":{"type":"string","format":"uuid"}}],"responses":{"200":{"description":"Documents retrieved","content":{"*/*":{"schema":{"$ref":"#/components/schemas/PageDocumentSummaryDto"}}}},"404":{"description":"Patient not found","content":{"*/*":{"schema":{"$ref":"#/components/schemas/PageDocumentSummaryDto"}}}}}}},"/api/v1/dental-charts/patient/{patientId}":{"get":{"tags":["Dental Charts"],"summary":"Get patient dental chart","description":"Retrieves the complete dental chart showing all tooth conditions for a patient.","operationId":"getPatientDentalChart","parameters":[{"name":"patientId","in":"path","description":"Patient UUID","required":true,"schema":{"type":"string","format":"uuid"}}],"responses":{"200":{"description":"Dental chart retrieved","content":{"*/*":{"schema":{"$ref":"#/components/schemas/DentalChartDto"}}}},"404":{"description":"Patient not found","content":{"*/*":{"schema":{"$ref":"#/components/schemas/DentalChartDto"}}}}}}},"/api/v1/appointments/{id}":{"get":{"tags":["Appointments"],"summary":"Get appointment by ID","description":"Retrieves a specific appointment by its UUID.","operationId":"getAppointmentById","parameters":[{"name":"id","in":"path","description":"Appointment UUID","required":true,"schema":{"type":"string","format":"uuid"}}],"responses":{"200":{"description":"Appointment found","content":{"*/*":{"schema":{"$ref":"#/components/schemas/AppointmentCardDto"}}}},"404":{"description":"Appointment not found","content":{"*/*":{"schema":{"$ref":"#/components/schemas/AppointmentCardDto"}}}}}}},"/api/v1/appointments/patient/{patientId}":{"get":{"tags":["Appointments"],"summary":"Get all appointments for patient","description":"Retrieves paginated list of all appointments for a specific patient.","operationId":"getPatientAppointments","parameters":[{"name":"page","in":"query","description":"Zero-based page index (0..N)","example":0},{"name":"size","in":"query","description":"The size of the page to be returned","example":20},{"name":"sort","in":"query","description":"Sorting criteria: property(,asc|desc). Default: appointmentDateTime","example":"appointmentDateTime"},{"name":"patientId","in":"path","description":"Patient UUID","required":true,"schema":{"type":"string","format":"uuid"}}],"responses":{"200":{"description":"Patient appointments retrieved","content":{"*/*":{"schema":{"$ref":"#/components/schemas/PageAppointmentCardDto"}}}},"404":{"description":"Patient not found","content":{"*/*":{"schema":{"$ref":"#/components/schemas/PageAppointmentCardDto"}}}}}}},"/api/v1/appointments/patient/{patientId}/upcoming":{"get":{"tags":["Appointments"],"summary":"Get upcoming appointments for patient","description":"Retrieves upcoming appointments for a specific patient.","operationId":"getUpcomingAppointmentsForPatient","parameters":[{"name":"patientId","in":"path","description":"Patient UUID","required":true,"schema":{"type":"string","format":"uuid"}}],"responses":{"200":{"description":"Upcoming appointments retrieved","content":{"*/*":{"schema":{"type":"array","items":{"$ref":"#/components/schemas/UpcomingAppointmentDto"}}}}},"404":{"description":"Patient not found","content":{"*/*":{"schema":{"type":"array","items":{"$ref":"#/components/schemas/UpcomingAppointmentDto"}}}}}}}},"/api/v1/appointments/date/{date}":{"get":{"tags":["Appointments"],"summary":"Get appointments for specific date","description":"Retrieves all appointments for a specific date (today's appointments).","operationId":"getAppointmentsForDate","parameters":[{"name":"date","in":"path","description":"Date in YYYY-MM-DD format","required":true,"schema":{"type":"string","format":"date"}}],"responses":{"200":{"description":"Appointments retrieved","content":{"*/*":{"schema":{"type":"array","items":{"$ref":"#/components/schemas/AppointmentCardDto"}}}}}}}},"/api/v1/appointments/date-range":{"get":{"tags":["Appointments"],"summary":"Get appointments by date range","description":"Retrieves appointments within a specific date/time range for daily view in sidebar.","operationId":"getAppointmentsByDateRange","parameters":[{"name":"startDateTime","in":"query","description":"Start date and time (ISO format)","required":true,"schema":{"type":"string","format":"date-time"}},{"name":"endDateTime","in":"query","description":"End date and time (ISO format)","required":true,"schema":{"type":"string","format":"date-time"}}],"responses":{"200":{"description":"Appointments retrieved","content":{"*/*":{"schema":{"type":"array","items":{"$ref":"#/components/schemas/AppointmentCardDto"}}}}}}}}},"components":{"schemas":{"TreatmentCreateRequest":{"type":"object","properties":{"treatmentDate":{"type":"string","format":"date"},"treatmentTime":{"type":"string"},"toothNumber":{"type":"integer","format":"int32"},"procedureId":{"type":"string","format":"uuid"},"materialUsed":{"type":"string"},"quantity":{"type":"integer","format":"int32"},"cost":{"type":"number"},"status":{"type":"string","enum":["PLANNED","IN_PROGRESS","COMPLETED","CANCELLED","SCHEDULED"]},"doctorId":{"type":"string","format":"uuid"},"assistantName":{"type":"string"},"sessionNumber":{"type":"string"},"durationMinutes":{"type":"integer","format":"int32"},"treatmentNotes":{"type":"string"},"postTreatmentInstructions":{"type":"string"}},"required":["cost","doctorId","procedureId","status","treatmentDate","treatmentTime"]},"TreatmentLogDto":{"type":"object","properties":{"treatmentId":{"type":"string","format":"uuid"},"treatmentDate":{"type":"string","format":"date"},"treatmentTime":{"type":"string"},"visitType":{"type":"string"},"toothNumber":{"type":"integer","format":"int32"},"treatmentName":{"type":"string"},"doctorName":{"type":"string"},"durationMinutes":{"type":"integer","format":"int32"},"cost":{"type":"number"},"status":{"type":"string","enum":["PLANNED","IN_PROGRESS","COMPLETED","CANCELLED","SCHEDULED"]},"notes":{"type":"string"},"nextAppointment":{"type":"string","format":"date"}}},"TreatmentMaterialCreateRequest":{"type":"object","description":"Request to create a new treatment material record","properties":{"treatmentId":{"type":"string","format":"uuid","description":"Treatment ID","example":"550e8400-e29b-41d4-a716-446655440000"},"materialName":{"type":"string","description":"Material name","example":"Composite Resin","minLength":1},"quantity":{"type":"number","description":"Quantity used","example":2.5},"unit":{"type":"string","description":"Unit of measurement","example":"grams"},"costPerUnit":{"type":"number","description":"Cost per unit","example":15.0},"supplier":{"type":"string","description":"Supplier name","example":"3M Dental"},"batchNumber":{"type":"string","description":"Batch number","example":"BT2024001"},"notes":{"type":"string","description":"Additional notes","example":"High quality material"}},"required":["costPerUnit","materialName","quantity","treatmentId"]},"TreatmentMaterialDto":{"type":"object","description":"Treatment material information","properties":{"id":{"type":"string","format":"uuid","description":"Material ID","example":"550e8400-e29b-41d4-a716-446655440000"},"treatmentId":{"type":"string","format":"uuid","description":"Treatment ID","example":"550e8400-e29b-41d4-a716-446655440000"},"materialName":{"type":"string","description":"Material name","example":"Composite Resin"},"quantity":{"type":"number","description":"Quantity used","example":2.5},"unit":{"type":"string","description":"Unit of measurement","example":"grams"},"costPerUnit":{"type":"number","description":"Cost per unit","example":15.0},"totalCost":{"type":"number","description":"Total cost","example":37.5},"supplier":{"type":"string","description":"Supplier name","example":"3M Dental"},"batchNumber":{"type":"string","description":"Batch number","example":"BT2024001"},"notes":{"type":"string","description":"Additional notes","example":"High quality material"},"createdAt":{"type":"string","format":"date-time","description":"Creation timestamp"},"updatedAt":{"type":"string","format":"date-time","description":"Last update timestamp"}}},"StaffUpdateRequest":{"type":"object","properties":{"fullName":{"type":"string","maxLength":100,"minLength":0},"role":{"type":"string","enum":["DOCTOR","NURSE","ASSISTANT","RECEPTIONIST","ACCOUNTANT","ADMIN"]},"email":{"type":"string","maxLength":100,"minLength":0},"phoneNumber":{"type":"string","maxLength":30,"minLength":0},"specialtyIds":{"type":"array","items":{"type":"string","format":"uuid"},"uniqueItems":true},"active":{"type":"boolean"}},"required":["email","fullName","role"]},"SpecialtyDto":{"type":"object","properties":{"id":{"type":"string","format":"uuid"},"name":{"type":"string"},"description":{"type":"string"},"createdAt":{"type":"string","format":"date-time"},"updatedAt":{"type":"string","format":"date-time"},"active":{"type":"boolean"}}},"StaffDto":{"type":"object","properties":{"id":{"type":"string","format":"uuid"},"fullName":{"type":"string"},"role":{"type":"string","enum":["DOCTOR","NURSE","ASSISTANT","RECEPTIONIST","ACCOUNTANT","ADMIN"]},"email":{"type":"string"},"phoneNumber":{"type":"string"},"specialties":{"type":"array","items":{"$ref":"#/components/schemas/SpecialtyDto"},"uniqueItems":true},"createdAt":{"type":"string","format":"date-time"},"updatedAt":{"type":"string","format":"date-time"},"active":{"type":"boolean"}}},"SpecialtyUpdateRequest":{"type":"object","properties":{"name":{"type":"string","maxLength":100,"minLength":0},"description":{"type":"string"},"active":{"type":"boolean"}},"required":["name"]},"PatientUpdateRequest":{"type":"object","properties":{"fullName":{"type":"string","maxLength":150,"minLength":0},"dateOfBirth":{"type":"string","format":"date"},"gender":{"type":"string","maxLength":10,"minLength":0},"phoneNumber":{"type":"string","maxLength":30,"minLength":0},"email":{"type":"string","maxLength":100,"minLength":0},"address":{"type":"string"},"insuranceProvider":{"type":"string","maxLength":100,"minLength":0},"insuranceNumber":{"type":"string","maxLength":50,"minLength":0},"importantMedicalNotes":{"type":"string"}},"required":["dateOfBirth","fullName"]},"PatientSummaryDto":{"type":"object","properties":{"id":{"type":"string","format":"uuid"},"publicFacingId":{"type":"string"},"fullName":{"type":"string"},"dateOfBirth":{"type":"string","format":"date"},"age":{"type":"integer","format":"int32"},"gender":{"type":"string"},"phoneNumber":{"type":"string"},"email":{"type":"string"},"address":{"type":"string"},"insuranceProvider":{"type":"string"},"insuranceNumber":{"type":"string"},"importantMedicalNotes":{"type":"string"},"balance":{"type":"number"},"hasAlert":{"type":"boolean"}}},"NoteUpdateRequest":{"type":"object","properties":{"content":{"type":"string","maxLength":2000,"minLength":0},"noteType":{"type":"string","maxLength":100,"minLength":0}},"required":["content"]},"NoteSummaryDto":{"type":"object","properties":{"noteId":{"type":"string","format":"uuid"},"content":{"type":"string"},"createdByStaffName":{"type":"string"},"noteDate":{"type":"string","format":"date-time"},"createdAt":{"type":"string","format":"date-time"}}},"LabRequestDto":{"type":"object","properties":{"labRequestId":{"type":"string","format":"uuid"},"orderNumber":{"type":"string"},"itemDescription":{"type":"string"},"toothNumber":{"type":"integer","format":"int32"},"dateSent":{"type":"string","format":"date"},"dateDue":{"type":"string","format":"date"},"status":{"type":"string","enum":["PENDING","IN_PROGRESS","SENT","RECEIVED","CANCELLED"]},"labName":{"type":"string"}}},"ToothDto":{"type":"object","properties":{"toothNumber":{"type":"integer","format":"int32"},"conditionCode":{"type":"string"},"conditionName":{"type":"string"},"colorHex":{"type":"string"},"notes":{"type":"string"},"lastTreatmentDate":{"type":"string","format":"date"}}},"ClinicInfoUpdateRequest":{"type":"object","properties":{"name":{"type":"string","maxLength":255,"minLength":0},"address":{"type":"string"},"phoneNumber":{"type":"string","maxLength":50,"minLength":0},"email":{"type":"string","maxLength":100,"minLength":0},"timezone":{"type":"string","maxLength":50,"minLength":0}},"required":["name","timezone"]},"ClinicInfoDto":{"type":"object","properties":{"id":{"type":"boolean"},"name":{"type":"string"},"address":{"type":"string"},"phoneNumber":{"type":"string"},"email":{"type":"string"},"timezone":{"type":"string"},"createdAt":{"type":"string","format":"date-time"},"updatedAt":{"type":"string","format":"date-time"}}},"TreatmentSearchCriteria":{"type":"object","description":"Advanced search criteria for treatments","properties":{"patientId":{"type":"string","format":"uuid","description":"Filter by patient ID","example":"550e8400-e29b-41d4-a716-446655440000"},"doctorId":{"type":"string","format":"uuid","description":"Filter by doctor ID","example":"550e8400-e29b-41d4-a716-446655440000"},"procedureId":{"type":"string","format":"uuid","description":"Filter by procedure ID","example":"550e8400-e29b-41d4-a716-446655440000"},"statuses":{"type":"array","description":"Filter by treatment status","items":{"type":"string","enum":["PLANNED","IN_PROGRESS","COMPLETED","CANCELLED","SCHEDULED"]}},"toothNumber":{"type":"integer","format":"int32","description":"Filter by tooth number","example":11},"toothNumbers":{"type":"array","description":"Filter by tooth numbers","items":{"type":"integer","format":"int32"}},"treatmentDateFrom":{"type":"string","format":"date","description":"Filter by treatment date from","example":"2024-01-01"},"treatmentDateTo":{"type":"string","format":"date","description":"Filter by treatment date to","example":"2024-12-31"},"costFrom":{"type":"number","description":"Minimum treatment cost","example":100.0,"minimum":0.0},"costTo":{"type":"number","description":"Maximum treatment cost","example":500.0,"minimum":0.0},"notesContain":{"type":"string","description":"Search in treatment notes","example":"root canal"},"procedureName":{"type":"string","description":"Filter by procedure name","example":"filling"},"doctorName":{"type":"string","description":"Filter by doctor name","example":"Dr. Smith"},"patientName":{"type":"string","description":"Filter by patient name","example":"John Doe"},"hasMaterials":{"type":"boolean","description":"Filter treatments with materials used","example":true},"createdFrom":{"type":"string","format":"date","description":"Filter by creation date from","example":"2024-01-01"},"createdTo":{"type":"string","format":"date","description":"Filter by creation date to","example":"2024-12-31"}}},"PageTreatmentLogDto":{"type":"object","properties":{"totalElements":{"type":"integer","format":"int64"},"totalPages":{"type":"integer","format":"int32"},"first":{"type":"boolean"},"last":{"type":"boolean"},"size":{"type":"integer","format":"int32"},"content":{"type":"array","items":{"$ref":"#/components/schemas/TreatmentLogDto"}},"number":{"type":"integer","format":"int32"},"sort":{"$ref":"#/components/schemas/SortObject"},"numberOfElements":{"type":"integer","format":"int32"},"pageable":{"$ref":"#/components/schemas/SwaggerPageable"},"empty":{"type":"boolean"}}},"SortObject":{"type":"object","properties":{"empty":{"type":"boolean"},"sorted":{"type":"boolean"},"unsorted":{"type":"boolean"}}},"SwaggerPageable":{"type":"object","properties":{"page":{"type":"integer","format":"int32"},"size":{"type":"integer","format":"int32"},"sort":{"type":"string"}}},"TreatmentMaterialSearchCriteria":{"type":"object","description":"Advanced search criteria for treatment materials","properties":{"treatmentId":{"type":"string","format":"uuid","description":"Filter by treatment ID","example":"550e8400-e29b-41d4-a716-446655440000"},"patientId":{"type":"string","format":"uuid","description":"Filter by patient ID","example":"550e8400-e29b-41d4-a716-446655440000"},"materialName":{"type":"string","description":"Filter by material name","example":"Composite Resin"},"materialNames":{"type":"array","description":"Filter by multiple material names","items":{"type":"string"}},"materialNameContains":{"type":"string","description":"Search in material names","example":"composite"},"supplier":{"type":"string","description":"Filter by supplier","example":"3M Dental"},"suppliers":{"type":"array","description":"Filter by multiple suppliers","items":{"type":"string"}},"batchNumber":{"type":"string","description":"Filter by batch number","example":"BT2024001"},"unit":{"type":"string","description":"Filter by unit of measurement","example":"grams"},"quantityFrom":{"type":"number","description":"Minimum quantity used","example":1.0,"minimum":0.0},"quantityTo":{"type":"number","description":"Maximum quantity used","example":10.0,"minimum":0.0},"costPerUnitFrom":{"type":"number","description":"Minimum cost per unit","example":5.0,"minimum":0.0},"costPerUnitTo":{"type":"number","description":"Maximum cost per unit","example":50.0,"minimum":0.0},"totalCostFrom":{"type":"number","description":"Minimum total cost","example":10.0,"minimum":0.0},"totalCostTo":{"type":"number","description":"Maximum total cost","example":100.0,"minimum":0.0},"notesContain":{"type":"string","description":"Search in notes","example":"high quality"},"usedFrom":{"type":"string","format":"date","description":"Filter by usage date from","example":"2024-01-01"},"usedTo":{"type":"string","format":"date","description":"Filter by usage date to","example":"2024-12-31"},"createdFrom":{"type":"string","format":"date","description":"Filter by creation date from","example":"2024-01-01"},"createdTo":{"type":"string","format":"date","description":"Filter by creation date to","example":"2024-12-31"}}},"PageTreatmentMaterialDto":{"type":"object","properties":{"totalElements":{"type":"integer","format":"int64"},"totalPages":{"type":"integer","format":"int32"},"first":{"type":"boolean"},"last":{"type":"boolean"},"size":{"type":"integer","format":"int32"},"content":{"type":"array","items":{"$ref":"#/components/schemas/TreatmentMaterialDto"}},"number":{"type":"integer","format":"int32"},"sort":{"$ref":"#/components/schemas/SortObject"},"numberOfElements":{"type":"integer","format":"int32"},"pageable":{"$ref":"#/components/schemas/SwaggerPageable"},"empty":{"type":"boolean"}}},"StaffCreateRequest":{"type":"object","properties":{"fullName":{"type":"string","maxLength":100,"minLength":0},"role":{"type":"string","enum":["DOCTOR","NURSE","ASSISTANT","RECEPTIONIST","ACCOUNTANT","ADMIN"]},"email":{"type":"string","maxLength":100,"minLength":0},"phoneNumber":{"type":"string","maxLength":30,"minLength":0},"specialtyIds":{"type":"array","items":{"type":"string","format":"uuid"},"uniqueItems":true}},"required":["email","fullName","role"]},"StaffSearchCriteria":{"type":"object","properties":{"searchTerm":{"type":"string"},"role":{"type":"string","enum":["DOCTOR","NURSE","ASSISTANT","RECEPTIONIST","ACCOUNTANT","ADMIN"]},"specialtyIds":{"type":"array","items":{"type":"string","format":"uuid"},"uniqueItems":true},"isActive":{"type":"boolean"}}},"PageStaffDto":{"type":"object","properties":{"totalElements":{"type":"integer","format":"int64"},"totalPages":{"type":"integer","format":"int32"},"first":{"type":"boolean"},"last":{"type":"boolean"},"size":{"type":"integer","format":"int32"},"content":{"type":"array","items":{"$ref":"#/components/schemas/StaffDto"}},"number":{"type":"integer","format":"int32"},"sort":{"$ref":"#/components/schemas/SortObject"},"numberOfElements":{"type":"integer","format":"int32"},"pageable":{"$ref":"#/components/schemas/SwaggerPageable"},"empty":{"type":"boolean"}}},"SpecialtyCreateRequest":{"type":"object","properties":{"name":{"type":"string","maxLength":100,"minLength":0},"description":{"type":"string"}},"required":["name"]},"PatientCreateRequest":{"type":"object","properties":{"fullName":{"type":"string","maxLength":150,"minLength":0},"dateOfBirth":{"type":"string","format":"date"},"gender":{"type":"string","maxLength":10,"minLength":0},"phoneNumber":{"type":"string","maxLength":30,"minLength":0},"email":{"type":"string","maxLength":100,"minLength":0},"address":{"type":"string"},"insuranceProvider":{"type":"string","maxLength":100,"minLength":0},"insuranceNumber":{"type":"string","maxLength":50,"minLength":0},"importantMedicalNotes":{"type":"string"}},"required":["dateOfBirth","fullName"]},"PatientSearchCriteria":{"type":"object","description":"Advanced search criteria for patients","properties":{"searchTerm":{"type":"string","description":"General search term (name, ID, phone, email)","example":"John Doe"},"name":{"type":"string","description":"Filter by patient name","example":"John"},"publicFacingId":{"type":"string","description":"Filter by public facing ID","example":"P001"},"phoneNumber":{"type":"string","description":"Filter by phone number","example":123456789},"email":{"type":"string","description":"Filter by email address","example":"john@example.com"},"gender":{"type":"string","description":"Filter by gender","example":"Male"},"insuranceProvider":{"type":"string","description":"Filter by insurance provider","example":"BlueCross"},"insuranceNumber":{"type":"string","description":"Filter by insurance number","example":"INS123456"},"dateOfBirthFrom":{"type":"string","format":"date","description":"Filter by birth date from (inclusive)","example":"1980-01-01"},"dateOfBirthTo":{"type":"string","format":"date","description":"Filter by birth date to (inclusive)","example":"1990-12-31"},"ageFrom":{"type":"integer","format":"int32","description":"Minimum age","example":18,"minimum":0},"ageTo":{"type":"integer","format":"int32","description":"Maximum age","example":65,"minimum":0},"balanceFrom":{"type":"number","description":"Minimum balance","example":0.0,"minimum":0.0},"balanceTo":{"type":"number","description":"Maximum balance","example":1000.0,"minimum":0.0},"isActive":{"type":"boolean","description":"Filter by active status","example":true},"hasMedicalNotes":{"type":"boolean","description":"Filter patients with medical notes","example":true},"hasOutstandingBalance":{"type":"boolean","description":"Filter patients with outstanding balance","example":true},"createdFrom":{"type":"string","format":"date","description":"Filter by creation date from","example":"2024-01-01"},"createdTo":{"type":"string","format":"date","description":"Filter by creation date to","example":"2024-12-31"},"hasAppointments":{"type":"boolean","description":"Filter patients who had appointments","example":true},"hasTreatments":{"type":"boolean","description":"Filter patients who had treatments","example":true},"address":{"type":"string","description":"Filter by city or address","example":"New York"},"isBalanceNegative":{"type":"boolean","description":"Filter patients with negative balance","example":true}}},"PagePatientSummaryDto":{"type":"object","properties":{"totalElements":{"type":"integer","format":"int64"},"totalPages":{"type":"integer","format":"int32"},"first":{"type":"boolean"},"last":{"type":"boolean"},"size":{"type":"integer","format":"int32"},"content":{"type":"array","items":{"$ref":"#/components/schemas/PatientSummaryDto"}},"number":{"type":"integer","format":"int32"},"sort":{"$ref":"#/components/schemas/SortObject"},"numberOfElements":{"type":"integer","format":"int32"},"pageable":{"$ref":"#/components/schemas/SwaggerPageable"},"empty":{"type":"boolean"}}},"NoteCreateRequest":{"type":"object","properties":{"patientId":{"type":"string","format":"uuid"},"content":{"type":"string","maxLength":2000,"minLength":0},"noteType":{"type":"string","maxLength":100,"minLength":0}},"required":["content","patientId"]},"LabRequestCreateRequest":{"type":"object","properties":{"patientId":{"type":"string","format":"uuid"},"requestDate":{"type":"string","format":"date"},"labName":{"type":"string","maxLength":100,"minLength":0},"testType":{"type":"string","maxLength":100,"minLength":0},"instructions":{"type":"string","maxLength":500,"minLength":0},"expectedCompletionDate":{"type":"string","format":"date"},"priority":{"type":"string","maxLength":200,"minLength":0}},"required":["labName","patientId","requestDate","testType"]},"InvoiceCreateRequest":{"type":"object","properties":{"patientId":{"type":"string","format":"uuid"},"invoiceDate":{"type":"string","format":"date"},"dueDate":{"type":"string","format":"date"},"items":{"type":"array","items":{"$ref":"#/components/schemas/InvoiceItemRequest"}},"notes":{"type":"string","maxLength":500,"minLength":0}},"required":["dueDate","invoiceDate","items","patientId"]},"InvoiceItemRequest":{"type":"object","properties":{"procedureId":{"type":"string","format":"uuid"},"quantity":{"type":"integer","format":"int32"},"unitPrice":{"type":"number"},"description":{"type":"string","maxLength":200,"minLength":0}},"required":["procedureId","unitPrice"]},"FinancialRecordDto":{"type":"object","properties":{"recordId":{"type":"string","format":"uuid"},"invoiceNumber":{"type":"string"},"issueDate":{"type":"string","format":"date"},"dueDate":{"type":"string","format":"date"},"amount":{"type":"number"},"status":{"type":"string","enum":["OPEN","DRAFT","PENDING","UNPAID","PAID","PARTIALLY_PAID","OVERDUE","CANCELLED","COMPLETED"]},"installments":{"type":"array","items":{"$ref":"#/components/schemas/PaymentInstallmentDto"}}}},"PaymentInstallmentDto":{"type":"object","properties":{"description":{"type":"string"},"paymentDate":{"type":"string","format":"date"},"amount":{"type":"number"}}},"PaymentCreateRequest":{"type":"object","properties":{"amount":{"type":"number"},"paymentDate":{"type":"string","format":"date"},"paymentMethod":{"type":"string","maxLength":50,"minLength":0},"notes":{"type":"string","maxLength":500,"minLength":0},"referenceNumber":{"type":"string","maxLength":100,"minLength":0}},"required":["amount","paymentDate","paymentMethod"]},"AppointmentCreateRequest":{"type":"object","description":"Request to create a new appointment","properties":{"specialtyId":{"type":"string","format":"uuid","description":"Specialty ID","example":"550e8400-e29b-41d4-a716-446655440000"},"patientId":{"type":"string","format":"uuid","description":"Patient ID","example":"550e8400-e29b-41d4-a716-446655440000"},"doctorId":{"type":"string","format":"uuid","description":"Doctor ID","example":"550e8400-e29b-41d4-a716-446655440000"},"appointmentDatetime":{"type":"string","format":"date-time","description":"Appointment date and time","example":"2024-07-15T10:30:00Z"},"durationMinutes":{"type":"integer","format":"int32","description":"Duration in minutes","example":30},"status":{"type":"string","description":"Appointment status","enum":["PENDING_CONFIRMATION","SCHEDULED","CONFIRMED","COMPLETED","CANCELLED","NO_SHOW"],"example":"SCHEDULED"},"notes":{"type":"string","description":"Additional notes","example":"Regular checkup"},"createdById":{"type":"string","format":"uuid","description":"Staff member who created the appointment"}},"required":["appointmentDatetime","durationMinutes","patientId","specialtyId"]},"AppointmentCardDto":{"type":"object","properties":{"appointmentId":{"type":"string","format":"uuid"},"patientId":{"type":"string","format":"uuid"},"patientFullName":{"type":"string"},"patientPublicId":{"type":"string"},"startTime":{"type":"string"},"endTime":{"type":"string"},"appointmentType":{"type":"string"},"practitionerTag":{"type":"string"},"patientPhoneNumber":{"type":"string"},"patientGender":{"type":"string"},"isActive":{"type":"boolean"},"hasFinancialAlert":{"type":"boolean"},"status":{"type":"string","enum":["PENDING_CONFIRMATION","SCHEDULED","CONFIRMED","COMPLETED","CANCELLED","NO_SHOW"]}}},"PageSpecialtyDto":{"type":"object","properties":{"totalElements":{"type":"integer","format":"int64"},"totalPages":{"type":"integer","format":"int32"},"first":{"type":"boolean"},"last":{"type":"boolean"},"size":{"type":"integer","format":"int32"},"content":{"type":"array","items":{"$ref":"#/components/schemas/SpecialtyDto"}},"number":{"type":"integer","format":"int32"},"sort":{"$ref":"#/components/schemas/SortObject"},"numberOfElements":{"type":"integer","format":"int32"},"pageable":{"$ref":"#/components/schemas/SwaggerPageable"},"empty":{"type":"boolean"}}},"PageProcedureSummaryDto":{"type":"object","properties":{"totalElements":{"type":"integer","format":"int64"},"totalPages":{"type":"integer","format":"int32"},"first":{"type":"boolean"},"last":{"type":"boolean"},"size":{"type":"integer","format":"int32"},"content":{"type":"array","items":{"$ref":"#/components/schemas/ProcedureSummaryDto"}},"number":{"type":"integer","format":"int32"},"sort":{"$ref":"#/components/schemas/SortObject"},"numberOfElements":{"type":"integer","format":"int32"},"pageable":{"$ref":"#/components/schemas/SwaggerPageable"},"empty":{"type":"boolean"}}},"ProcedureSummaryDto":{"type":"object","properties":{"procedureId":{"type":"string","format":"uuid"},"procedureCode":{"type":"string"},"name":{"type":"string"},"description":{"type":"string"},"defaultCost":{"type":"number"},"defaultDurationMinutes":{"type":"integer","format":"int32"},"specialtyName":{"type":"string"}}},"PageNoteSummaryDto":{"type":"object","properties":{"totalElements":{"type":"integer","format":"int64"},"totalPages":{"type":"integer","format":"int32"},"first":{"type":"boolean"},"last":{"type":"boolean"},"size":{"type":"integer","format":"int32"},"content":{"type":"array","items":{"$ref":"#/components/schemas/NoteSummaryDto"}},"number":{"type":"integer","format":"int32"},"sort":{"$ref":"#/components/schemas/SortObject"},"numberOfElements":{"type":"integer","format":"int32"},"pageable":{"$ref":"#/components/schemas/SwaggerPageable"},"empty":{"type":"boolean"}}},"PageLabRequestDto":{"type":"object","properties":{"totalElements":{"type":"integer","format":"int64"},"totalPages":{"type":"integer","format":"int32"},"first":{"type":"boolean"},"last":{"type":"boolean"},"size":{"type":"integer","format":"int32"},"content":{"type":"array","items":{"$ref":"#/components/schemas/LabRequestDto"}},"number":{"type":"integer","format":"int32"},"sort":{"$ref":"#/components/schemas/SortObject"},"numberOfElements":{"type":"integer","format":"int32"},"pageable":{"$ref":"#/components/schemas/SwaggerPageable"},"empty":{"type":"boolean"}}},"PageFinancialRecordDto":{"type":"object","properties":{"totalElements":{"type":"integer","format":"int64"},"totalPages":{"type":"integer","format":"int32"},"first":{"type":"boolean"},"last":{"type":"boolean"},"size":{"type":"integer","format":"int32"},"content":{"type":"array","items":{"$ref":"#/components/schemas/FinancialRecordDto"}},"number":{"type":"integer","format":"int32"},"sort":{"$ref":"#/components/schemas/SortObject"},"numberOfElements":{"type":"integer","format":"int32"},"pageable":{"$ref":"#/components/schemas/SwaggerPageable"},"empty":{"type":"boolean"}}},"DocumentSummaryDto":{"type":"object","properties":{"documentId":{"type":"string","format":"uuid"},"fileName":{"type":"string"},"fileType":{"type":"string"},"mimeType":{"type":"string"},"uploadDate":{"type":"string","format":"date-time"},"fileSizeBytes":{"type":"integer","format":"int64"},"uploadedByStaffName":{"type":"string"}}},"PageDocumentSummaryDto":{"type":"object","properties":{"totalElements":{"type":"integer","format":"int64"},"totalPages":{"type":"integer","format":"int32"},"first":{"type":"boolean"},"last":{"type":"boolean"},"size":{"type":"integer","format":"int32"},"content":{"type":"array","items":{"$ref":"#/components/schemas/DocumentSummaryDto"}},"number":{"type":"integer","format":"int32"},"sort":{"$ref":"#/components/schemas/SortObject"},"numberOfElements":{"type":"integer","format":"int32"},"pageable":{"$ref":"#/components/schemas/SwaggerPageable"},"empty":{"type":"boolean"}}},"PatientBalanceSummaryDto":{"type":"object","properties":{"totalBalance":{"type":"number"},"balanceStatus":{"type":"string"},"balanceDescription":{"type":"string"}}},"PatientFinancialSummaryView":{"type":"object","properties":{"id":{"type":"string","format":"uuid"},"fullName":{"type":"string"},"publicFacingId":{"type":"string"},"balance":{"type":"number"},"totalInvoices":{"type":"integer","format":"int64"},"unpaidInvoices":{"type":"integer","format":"int64"},"totalUnpaid":{"type":"number"}}},"DentalChartDto":{"type":"object","properties":{"teeth":{"type":"array","items":{"$ref":"#/components/schemas/ToothDto"}}}},"PageAppointmentCardDto":{"type":"object","properties":{"totalElements":{"type":"integer","format":"int64"},"totalPages":{"type":"integer","format":"int32"},"first":{"type":"boolean"},"last":{"type":"boolean"},"size":{"type":"integer","format":"int32"},"content":{"type":"array","items":{"$ref":"#/components/schemas/AppointmentCardDto"}},"number":{"type":"integer","format":"int32"},"sort":{"$ref":"#/components/schemas/SortObject"},"numberOfElements":{"type":"integer","format":"int32"},"pageable":{"$ref":"#/components/schemas/SwaggerPageable"},"empty":{"type":"boolean"}}},"UpcomingAppointmentDto":{"type":"object","properties":{"appointmentId":{"type":"string","format":"uuid"},"appointmentDateTime":{"type":"string","format":"date-time"},"specialty":{"type":"string"},"treatmentType":{"type":"string"},"doctorName":{"type":"string"},"status":{"type":"string","enum":["PENDING_CONFIRMATION","SCHEDULED","CONFIRMED","COMPLETED","CANCELLED","NO_SHOW"]},"durationMinutes":{"type":"integer","format":"int32"}}}}}}
